climsight/__init__.py
climsight/climate_functions.py
climsight/climsight.py
climsight/climsight_classes.py
climsight/climsight_engine.py
climsight/data_container.py
climsight/economic_functions.py
climsight/environmental_functions.py
climsight/evaluation.py
climsight/evaluation_paper.py
climsight/extract_climatedata_functions.py
climsight/geo_functions.py
climsight/launch.py
climsight/rag.py
climsight/smart_agent.py
climsight/stream_handler.py
climsight/streamlit_interface.py
climsight/terminal_interface.py
climsight/test_engine.py
climsight/test_interfaces.py
climsight-1.0.0.dist-info/LICENSE
climsight-1.0.0.dist-info/METADATA
climsight-1.0.0.dist-info/WHEEL
climsight-1.0.0.dist-info/entry_points.txt
climsight-1.0.0.dist-info/top_level.txt
climsight-1.0.0.dist-info/RECORD
