Metadata-Version: 2.2
Name: climsight
Version: 1.0.0
Summary: A tool that combines LLMs with climate data to provide localized insights for decision-making in agriculture, urban planning, disaster management, and policy development.
Author: kuivi, AntoniaJost, koldunovn, dmpantiu, boryasbora
License: BSD-3-Clause
Project-URL: Source, https://github.com/CliDyn/climsight
Project-URL: Citation, https://doi.org/10.1038/s43247-023-01199-1
Keywords: climate,llm,climate-assessment,rag,decision-support
License-File: LICENSE
Requires-Dist: streamlit
Requires-Dist: xarray
Requires-Dist: geopy
Requires-Dist: geopandas
Requires-Dist: pyproj
Requires-Dist: requests
Requires-Dist: requests-mock
Requires-Dist: pandas
Requires-Dist: folium
Requires-Dist: langchain
Requires-Dist: streamlit-folium
Requires-Dist: netcdf4
Requires-Dist: dask
Requires-Dist: pip
Requires-Dist: osmnx
Requires-Dist: matplotlib
Requires-Dist: openai
Requires-Dist: langchain-community
Requires-Dist: langchain-openai
Requires-Dist: langchain-chroma
Requires-Dist: langchain-core
Requires-Dist: pydantic
Requires-Dist: langgraph
Requires-Dist: bs4
Requires-Dist: wikipedia
Requires-Dist: scipy
Requires-Dist: pyproj
